i6/__init__.py
i6/__main__.py
i6/classes/Base.py
i6/classes/List.py
i6/classes/__init__.py
i6/cli/__init__.py
i6/cli/main.py
i6/container/ContainerCommand.py
i6/container/__init__.py
i6/crypto/AES.py
i6/crypto/__init__.py
i6/crypto/functions.py
i6/db/__init__.py
i6/errors/__init__.py
i6/ftp/__init__.py
i6/git/__init__.py
i6/http/Result.py
i6/http/__init__.py
i6/log/__init__.py
i6/shell/__init__.py
i6/util/__init__.py
i6-0.0.5.dist-info/LICENCE
i6-0.0.5.dist-info/METADATA
i6-0.0.5.dist-info/WHEEL
i6-0.0.5.dist-info/entry_points.txt
i6-0.0.5.dist-info/top_level.txt
i6-0.0.5.dist-info/zip-safe
i6-0.0.5.dist-info/RECORD
