Metadata-Version: 2.1
Name: i6
Version: 0.0.5
Summary: A standardized collection of python libs and tools
Home-page: https://github.com/kruserr/i6
Author: kruserr
License: UNKNOWN
Project-URL: Documentation, https://github.com/kruserr/i6/wiki
Project-URL: Source, https://github.com/kruserr/i6
Keywords: i6 toolchain collection libs tools
Platform: UNKNOWN
Classifier: Topic :: Software Development
Classifier: Development Status :: 1 - Planning
Classifier: Intended Audience :: Developers
Classifier: Programming Language :: Python :: 3
Classifier: License :: OSI Approved :: MIT License
Classifier: Operating System :: OS Independent
Requires-Python: >=3.7
Requires-Dist: docker
Requires-Dist: pyftpdlib
Requires-Dist: SQLAlchemy
Requires-Dist: marshmallow
Requires-Dist: cryptography
